raumo_data_tools/__init__.py
raumo_data_tools/chart_tools/__init__.py
raumo_data_tools/chart_tools/lib_plotly_figures.py
raumo_data_tools/config_handler.py
raumo_data_tools/configs/data_format.json
raumo_data_tools/influx_reader.py
raumo_data_tools/influx_writer.py
raumo_data_tools/matomo_api.py
raumo_data_tools/matomo_handler.py
raumo_data_tools/pipelines.py
raumo_data_tools/secrets/influx.json
raumo_data_tools/test_influx_writer.py
raumo_data_tools/time_handler.py
raumo_data_tools-0.1.6.dist-info/WHEEL
raumo_data_tools-0.1.6.dist-info/METADATA
raumo_data_tools-0.1.6.dist-info/RECORD
